pytorch_gmm/__init__.py
pytorch_gmm/gmm.py
pytorch_gmm-0.1.1.dist-info/licenses/LICENSE
pytorch_gmm-0.1.1.dist-info/METADATA
pytorch_gmm-0.1.1.dist-info/WHEEL
pytorch_gmm-0.1.1.dist-info/top_level.txt
pytorch_gmm-0.1.1.dist-info/RECORD
