Metadata-Version: 2.4
Name: pytorch-gmm
Version: 0.1.1
Summary: Fast PyTorch implementation of Gaussian mixture model (GMM)
Requires-Python: >=3.11
License-File: LICENSE
Requires-Dist: numpy>=1.24.0
Requires-Dist: torch>=2.0.0
Requires-Dist: tqdm>=4.4.1
Dynamic: license-file
